manman/__init__.py
manman/__main__.py
manman/cli.py
manman/detachable_tabs.py
manman/helpers.py
manman/manman.py
manman-1.1.1.dist-info/METADATA
manman-1.1.1.dist-info/WHEEL
manman-1.1.1.dist-info/licenses/LICENSE
manman-1.1.1.dist-info/RECORD
