Metadata-Version: 2.4
Name: manman
Version: 1.1.1
Summary: GUI for deployment and monitoring of servers and applications
Project-URL: Homepage, https://github.com/ASukhanov/manman
Author-email: Andrei Sukhanov <cyxandr@gmail.com>
License-File: LICENSE
Classifier: License :: OSI Approved :: MIT License
Classifier: Operating System :: OS Independent
Classifier: Programming Language :: Python :: 3
Requires-Python: >=3.7
Requires-Dist: qtpy
